dplpy/__init__.py
dplpy/__main__.py
dplpy/autoreg.py
dplpy/chron.py
dplpy/chron_stabilized.py
dplpy/create_json.py
dplpy/curvefit.py
dplpy/detrend.py
dplpy/dplpy.py
dplpy/plot.py
dplpy/rbar.py
dplpy/readers.py
dplpy/report.py
dplpy/series_corr.py
dplpy/smoothingspline.py
dplpy/stats.py
dplpy/summary.py
dplpy/tbrm.py
dplpy/template.py
dplpy/writers.py
dplpy/xdate.py
dplpy-0.1.5.dist-info/LICENSE
dplpy-0.1.5.dist-info/METADATA
dplpy-0.1.5.dist-info/WHEEL
dplpy-0.1.5.dist-info/top_level.txt
dplpy-0.1.5.dist-info/RECORD
