Metadata-Version: 2.1
Name: dplpy
Version: 0.1.5
Summary: Dendrochronology Program Library for Python
Author-email: Tyson Lee Swetnam <tswetnam@arizona.edu>, Ifeoluwa Ale <ifeoluwaale@arizona.edu>, Kevin Anchukaitis <kanchukaitis@arizona.edu>
License: GNU GENERAL PUBLIC LICENSE
Requires-Python: >=3.10
License-File: LICENSE
Requires-Dist: pandas >=2.0.0
Requires-Dist: csaps ==1.1.0
Requires-Dist: matplotlib >=3.8.0
Requires-Dist: scipy >=1.11.3
Requires-Dist: numpy <2,>=1.22.4 ; python_version < "3.11"
Requires-Dist: numpy <2,>=1.23.2 ; python_version == "3.11"
Requires-Dist: statsmodels >=0.13.5 ; python_version >= "3.10"
Requires-Dist: numpy <2,>=1.26.0 ; python_version >= "3.12"
Requires-Dist: statsmodels >=0.14.0 ; python_version >= "3.12"
